qingcloud_init-0.1.2.dist-info/DESCRIPTION.rst
qingcloud_init-0.1.2.dist-info/METADATA
qingcloud_init-0.1.2.dist-info/RECORD
qingcloud_init-0.1.2.dist-info/WHEEL
qingcloud_init-0.1.2.dist-info/entry_points.txt
qingcloud_init-0.1.2.dist-info/metadata.json
qingcloud_init-0.1.2.dist-info/top_level.txt
qinginit/__init__.py
qinginit/cli.py
qinginit/example.yml
