Metadata-Version: 2.0
Name: qingcloud-init
Version: 0.1.2
Summary: Qinginit is a setup script for qingcloud.
Home-page: https://xuanwo.org/
Author: Xuanwo
Author-email: xuanwo.cn@gmail.com
License: MIT License
Keywords: qigncloud,script
Platform: UNKNOWN
Classifier: Development Status :: 4 - Beta
Classifier: Environment :: Console
Classifier: License :: OSI Approved :: MIT License
Classifier: Operating System :: MacOS
Classifier: Operating System :: POSIX
Classifier: Operating System :: POSIX :: Linux
Classifier: Operating System :: Microsoft :: Windows
Classifier: Programming Language :: Python
Classifier: Programming Language :: Python :: 3.3
Classifier: Programming Language :: Python :: 3.4
Classifier: Programming Language :: Python :: 3.5
Requires-Dist: docopt
Requires-Dist: pyyaml
Requires-Dist: qingcloud-sdk
